cronlog.py
crontab.py
crontabs.py
python_crontab-3.0.0.dist-info/AUTHORS
python_crontab-3.0.0.dist-info/COPYING
python_crontab-3.0.0.dist-info/METADATA
python_crontab-3.0.0.dist-info/WHEEL
python_crontab-3.0.0.dist-info/top_level.txt
python_crontab-3.0.0.dist-info/RECORD
