Metadata-Version: 2.1
Name: python-crontab
Version: 3.0.0
Summary: Python Crontab API
Home-page: https://gitlab.com/doctormo/python-crontab/
Author: Martin Owens
Author-email: doctormo@gmail.com
License: LGPLv3
Platform: linux
Classifier: Development Status :: 5 - Production/Stable
Classifier: Development Status :: 6 - Mature
Classifier: Intended Audience :: Developers
Classifier: Intended Audience :: Information Technology
Classifier: Intended Audience :: System Administrators
Classifier: License :: OSI Approved :: GNU Lesser General Public License v3 or later (LGPLv3+)
Classifier: Operating System :: POSIX
Classifier: Operating System :: POSIX :: Linux
Classifier: Operating System :: POSIX :: SunOS/Solaris
Classifier: Programming Language :: Python
Classifier: Programming Language :: Python :: 3.5
Classifier: Programming Language :: Python :: 3.6
Classifier: Programming Language :: Python :: 3.7
Classifier: Programming Language :: Python :: 3.8
Classifier: Programming Language :: Python :: 3.9
Classifier: Programming Language :: Python :: 3.10
Provides: crontab
Provides: crontabs
Provides: cronlog
Provides-Extra: cron-schedule
Provides-Extra: cron-description
License-File: COPYING
License-File: AUTHORS
